{
  "data": {
    "fund_company": "    华安基金管理有限公司成立于1998年6月4日,是中国证监会批准成立的首批基金管理公司之一,主营业务包括基金发起设立、基金管理和中国证监会批准的其他业务,注册资本1.5亿元人民币,上海电气(集团)总公司、上海国际信托有限公司、上海工业投资(集团)有限公司、上海锦江国际投资管理有限公司、上海沸点投资发展有限公司分别持有华安基金管理有限公司20%的股权。目前华安旗下共管理了2只封闭式证券投资基金和8只开放式基金、1只ETF和1只外币基金,它们分别是:基金安信、基金安顺、华安创新证券投资基金、华安MSCI中国A股指数增强型证券投资基金、华安现金富利投资基金、华安宝利配置证券投资基金、华安宏利股票证券投资基金、华安中小盘成长股票型基金、华安策略优选股票型基金、华安稳定收益债券型证券投资基金、上证180交易型开放式指数证券投资基金、华安国际配置基金。",
    "fund_position": {
      "stock_percent": 94.04,
      "bond_percent": 0.19,
      "cash_percent": 5.56,
      "other_percent": 0.21,
      "asset_tot": 151495594.37,
      "asset_val": 150661796.22,
      "source_mark": "第三季度报",
      "source": "4",
      "enddate": "2020-09-30",
      "stock_list": [
        {
          "name": "浪潮信息",
          "code": "000977",
          "percent": 5.01,
          "current_price": 28.3,
          "change_percentage": -0.95,
          "xq_symbol": "SZ000977",
          "xq_url": "https://xueqiu.com/S/SZ000977",
          "amarket": true
        },
        {
          "name": "天赐材料",
          "code": "002709",
          "percent": 4.17,
          "current_price": 84.25,
          "change_percentage": 10,
          "xq_symbol": "SZ002709",
          "xq_url": "https://xueqiu.com/S/SZ002709",
          "amarket": true
        },
        {
          "name": "环旭电子",
          "code": "601231",
          "percent": 2.5,
          "current_price": 21.62,
          "change_percentage": -0.46,
          "xq_symbol": "SH601231",
          "xq_url": "https://xueqiu.com/S/SH601231",
          "amarket": true
        },
        {
          "name": "顺网科技",
          "code": "300113",
          "percent": 2.35,
          "current_price": 18.2,
          "change_percentage": 3.7,
          "xq_symbol": "SZ300113",
          "xq_url": "https://xueqiu.com/S/SZ300113",
          "amarket": true
        },
        {
          "name": "歌尔股份",
          "code": "002241",
          "percent": 1.9,
          "current_price": 37.16,
          "change_percentage": -2.24,
          "xq_symbol": "SZ002241",
          "xq_url": "https://xueqiu.com/S/SZ002241",
          "amarket": true
        },
        {
          "name": "中环股份",
          "code": "002129",
          "percent": 1.67,
          "current_price": 23.74,
          "change_percentage": -1.58,
          "xq_symbol": "SZ002129",
          "xq_url": "https://xueqiu.com/S/SZ002129",
          "amarket": true
        },
        {
          "name": "鹏鼎控股",
          "code": "002938",
          "percent": 1.54,
          "current_price": 54.51,
          "change_percentage": -2.14,
          "xq_symbol": "SZ002938",
          "xq_url": "https://xueqiu.com/S/SZ002938",
          "amarket": true
        },
        {
          "name": "飞亚达",
          "code": "000026",
          "percent": 1.33,
          "current_price": 12.5,
          "change_percentage": -1.03,
          "xq_symbol": "SZ000026",
          "xq_url": "https://xueqiu.com/S/SZ000026",
          "amarket": true
        },
        {
          "name": "鼎龙股份",
          "code": "300054",
          "percent": 1.29,
          "current_price": 16.22,
          "change_percentage": -1.1,
          "xq_symbol": "SZ300054",
          "xq_url": "https://xueqiu.com/S/SZ300054",
          "amarket": true
        },
        {
          "name": "三七互娱",
          "code": "002555",
          "percent": 1.23,
          "current_price": 29.38,
          "change_percentage": 4,
          "xq_symbol": "SZ002555",
          "xq_url": "https://xueqiu.com/S/SZ002555",
          "amarket": true
        }
      ],
      "bond_list": [
        {
          "name": "歌尔转2",
          "code": "128112",
          "percent": 0.13,
          "xq_symbol": "128112",
          "xq_url": "https://xueqiu.com/S/128112",
          "amarket": false
        },
        {
          "name": "联创转债",
          "code": "128101",
          "percent": 0.02,
          "xq_symbol": "128101",
          "xq_url": "https://xueqiu.com/S/128101",
          "amarket": false
        },
        {
          "name": "欣旺转债",
          "code": "123058",
          "percent": 0.01,
          "xq_symbol": "123058",
          "xq_url": "https://xueqiu.com/S/123058",
          "amarket": false
        },
        {
          "name": "安20转债",
          "code": "113592",
          "percent": 0.01,
          "xq_symbol": "113592",
          "xq_url": "https://xueqiu.com/S/113592",
          "amarket": false
        },
        {
          "name": "裕同转债",
          "code": "128104",
          "percent": 0.01,
          "xq_symbol": "128104",
          "xq_url": "https://xueqiu.com/S/128104",
          "amarket": false
        },
        {
          "name": "恩捷转债",
          "code": "128095",
          "percent": 0.01,
          "xq_symbol": "128095",
          "xq_url": "https://xueqiu.com/S/128095",
          "amarket": false
        }
      ]
    },
    "fund_rates": {
      "fd_code": "000549",
      "subscribe_rate": "0",
      "declare_rate": "1.50",
      "withdraw_rate": "1.500",
      "discount": "0.1",
      "subscribe_discount": "1",
      "declare_discount": "0.1",
      "declare_rate_table": [
        {
          "name": "买入金额<100万",
          "value": "1.50"
        },
        {
          "name": "100万≤买入金额<300万",
          "value": "1.20"
        },
        {
          "name": "300万≤买入金额<500万",
          "value": "0.80"
        },
        {
          "name": "500万≤买入金额",
          "value": "1000.00"
        }
      ],
      "withdraw_rate_table": [
        {
          "name": "0天<持有期限<7天",
          "value": "1.500"
        },
        {
          "name": "7天≤持有期限<30天",
          "value": "0.750"
        },
        {
          "name": "30天≤持有期限<365天",
          "value": "0.500"
        },
        {
          "name": "1年≤持有期限<2年",
          "value": "0.250"
        },
        {
          "name": "2年≤持有期限",
          "value": "0.000"
        }
      ],
      "other_rate_table": [
        {
          "name": "基金托管费",
          "value": "0.25"
        },
        {
          "name": "基金管理费",
          "value": "1.50"
        }
      ]
    },
    "manager_list": [
      {
        "name": "翁启森",
        "resume": "    翁启森先生,工业工程学硕士,22年证券、基金行业从业经历,具有中国大陆基金从业资格。曾在台湾JP证券任金融产业分析师及投资经理,台湾摩根富林明投信投资管理部任基金经理,台湾中信证券投资总监助理,台湾保德信投信任基金经理。2008 年4 月加入华安基金管理有限公司,任全球投资部总监。2010年9月起担任华安香港精选股票型证券投资基金的基金经理。2011 年5 月起同时担任华安大中华升级股票型证券投资基金的基金经理。2014年6月起担任基金投资部兼全球投资部高级总监。2014年3月至2016 年9 月同时担任华安宏利混合型证券投资基金的基金经理。2014 年4 月起同时担任华安大国新经济股票型证券投资基金的基金经理。2014 年6 月起担任基金投资部兼全球投资部高级总监。2015 年2 月至2016年9 月同时担任华安安顺灵活配置混合型证券投资基金的基金经理。2015年 3 月起担任公司总经理助理。2015年3 月起同时担任华安物联网主题股票型证券投资基金的基金经理。2015年6月至2016 年9 月同时担任华安宝利配置证券投资基金、华安生态优先混合型证券投资基金的基金经理。",
        "work_year": "24",
        "achievement_list": [
          {
            "fund_code": "040004",
            "fundsname": "华安宝利配置混合",
            "post_date": "2015-06-16",
            "resi_date": "2016-09-21",
            "cp_rate": -20.7122
          },
          {
            "fund_code": "000294",
            "fundsname": "华安生态优先混合",
            "post_date": "2015-06-16",
            "resi_date": "2016-09-21",
            "cp_rate": -29.9153
          },
          {
            "fund_code": "001028",
            "fundsname": "华安物联网主题股票",
            "post_date": "2015-03-17",
            "cp_rate": 20.2
          },
          {
            "fund_code": "519909",
            "fundsname": "华安安顺混合",
            "post_date": "2015-02-17",
            "resi_date": "2016-09-21",
            "cp_rate": 1.2408
          },
          {
            "fund_code": "000549",
            "fundsname": "华安大国新经济股票",
            "post_date": "2014-04-15",
            "cp_rate": 206
          },
          {
            "fund_code": "040005",
            "fundsname": "华安宏利混合",
            "post_date": "2014-03-18",
            "resi_date": "2016-09-21",
            "cp_rate": 43.5372
          },
          {
            "fund_code": "040021",
            "fundsname": "华安大中华升级股票(QDII)",
            "post_date": "2011-05-17",
            "cp_rate": 58.6
          },
          {
            "fund_code": "040018",
            "fundsname": "华安香港精选股票(QDII)",
            "post_date": "2010-09-19",
            "cp_rate": 103
          }
        ]
      }
    ],
    "fund_date_conf": {
      "fd_code": "000549",
      "buy_confirm_date": 1,
      "buy_query_date": 1,
      "sale_confirm_date": 1,
      "sale_query_date": 3,
      "all_buy_days": 2,
      "all_sale_days": 4
    }
  },
  "result_code": 0
}