{
  "data": {
    "fund_company": "    汇添富基金成立于2005年2月,资产管理总规模超过5100亿元,是中国一流的综合性资产管理集团之一。公司总部设在上海,在北京、上海、广州、成都等地设有分公司,在上海和香港设有子公司——汇添富资本管理有限公司和汇添富资产管理(香港)有限公司。公司业务牌照齐全,是首批QDII基金管理人、专户资产管理人、RQFII基金管理人,以及社保基金境内委托投资管理人和境外配售策略委托投资管理人、保险资金投资管理人、特定客户资产管理人。\n    汇添富基金自成立以来,始终将投资业绩放在首位,形成了独树一帜的品牌优势,被誉为“选股专家”,并以优秀的长期投资业绩和一流的客户服务,赢得了广大基金持有人和海内外机构的认可和信赖。截至2016年年中,公司公募、专户、社保及特定客户资产管理业务协同发展,资产管理总规模超过5100亿元,其中公募资产管理规模为2862亿元,稳居行业前十;服务客户超过3500万人。\n    目前,汇添富基金已经发展成为长期业绩优异、产品布局完善、业务领域全面、资产管理规模居前的大型基金公司。公募业务方面,截至2016年年中,汇添富基金共管理62只开放式基金,涵盖股票型基金、指数型基金、QDII基金、混合型基金、保本型基金、债券型基金、理财基金及货币市场基金等各类产品。公司立志于做中国证券市场的选股专家, 并已形成一整套行之有效的独特个股研究方法,旗下基金的投资业绩也因此获得了投资者的充分认可。截止2016年年中,公司累计为基金持有人盈利超过700亿元。\n    汇添富基金是业内最先布局互联网金融的基金公司。公司于2009年7月推出了业内首个基金电子账户“现金宝”,经过多年耕耘,目前汇添富现金宝平台保有量接近900亿元,个人客户保有量超过1800万人,机构客户超过2万户。平台账户2015年累计成交量超过12000亿元,“现金宝APP”下载量超过2.4亿次。\n    汇添富基金在业内率先获得QDII资格,也是业内最早一批获准设立海外子公司的基金管理公司。汇添富资产管理(香港)有限公司于2009年11月正式成立,目前同时拥有RQFII和QFII牌照,是汇添富基金开展跨境业务和合作的重要平台。\n    汇添富基金在业内首批获得了专户资产管理资格,最早组建了实力强大的专业团队率先开展专户业务,积累了丰富的专户资产管理经验,并拥有出色的投资管理业绩。截至2016年年中,汇添富基金专户资产规模接近1000亿,位居行业前列。\n    汇添富基金拥有社保基金境内委托投资管理人资格,所管理的社保组合投资业绩连续多年领先。2015年12月,汇添富基金再次获得社保基金境外配售策略委托投资管理人资格。\n    2013年初,汇添富基金设立了汇添富资本管理有限公司,业务范围为特定客户资产管理业务以及中国证监会许可的其他业务。未来汇添富资本将积极拓展非二级市场投资管理业务,包括逐步参与资产证券化投资、股权投资等领域。\n    公司自成立以来屡获殊荣,多次获得中国基金业金牛奖、中国明星基金奖、中国金基金奖、金鼎奖等多项业内重量级奖项。除此之外,汇添富基金还收获了“最受尊敬基金公司奖”、“最佳管理团队”、“最佳创新产品”、“最佳投资者教育”、“上海市金融创新奖一等奖”、“卓越雇主——中国最适宜工作的公司”等一系列大奖。\n    汇添富基金坚持强调完善的公司治理体系和科学的公司治理文化,是亚洲公司治理协会(ACGA)的首家中国会员企业。汇添富基金致力于为员工提供完善的个人职业发展规划和良好的工作与成长平台,并努力营造愉悦简单的工作氛围。\n    中国资产管理行业正迈入高速发展时期。汇添富基金的愿景是:通过全体员工的共同努力和长期艰苦不懈的奋斗,成为中国最受认可的资产管理品牌,发展成为中国最佳的资产管理公司之一,和全球资产管理行业最优秀的中国有关资产的管理人之一。",
    "fund_position": {
      "stock_percent": 90.08,
      "bond_percent": 0.07,
      "cash_percent": 9.67,
      "other_percent": 0.18,
      "asset_tot": 886512662.32,
      "asset_val": 879555050.06,
      "source_mark": "第三季度报",
      "source": "4",
      "enddate": "2020-09-30",
      "stock_list": [
        {
          "name": "万孚生物",
          "code": "300482",
          "percent": 1.34,
          "current_price": 90.13,
          "change_percentage": 1.03,
          "xq_symbol": "SZ300482",
          "xq_url": "https://xueqiu.com/S/SZ300482",
          "amarket": true
        },
        {
          "name": "安琪酵母",
          "code": "600298",
          "percent": 1.11,
          "current_price": 53,
          "change_percentage": 3.78,
          "xq_symbol": "SH600298",
          "xq_url": "https://xueqiu.com/S/SH600298",
          "amarket": true
        },
        {
          "name": "药石科技",
          "code": "300725",
          "percent": 1.08,
          "current_price": 135.4,
          "change_percentage": -1.88,
          "xq_symbol": "SZ300725",
          "xq_url": "https://xueqiu.com/S/SZ300725",
          "amarket": true
        },
        {
          "name": "金域医学",
          "code": "603882",
          "percent": 1.07,
          "current_price": 130.68,
          "change_percentage": 2,
          "xq_symbol": "SH603882",
          "xq_url": "https://xueqiu.com/S/SH603882",
          "amarket": true
        },
        {
          "name": "华大基因",
          "code": "300676",
          "percent": 1.03,
          "current_price": 127.59,
          "change_percentage": -0.75,
          "xq_symbol": "SZ300676",
          "xq_url": "https://xueqiu.com/S/SZ300676",
          "amarket": true
        },
        {
          "name": "国睿科技",
          "code": "600562",
          "percent": 1.01,
          "current_price": 17.71,
          "change_percentage": 4.05,
          "xq_symbol": "SH600562",
          "xq_url": "https://xueqiu.com/S/SH600562",
          "amarket": true
        },
        {
          "name": "华发股份",
          "code": "600325",
          "percent": 0.98,
          "current_price": 6.07,
          "change_percentage": -2.25,
          "xq_symbol": "SH600325",
          "xq_url": "https://xueqiu.com/S/SH600325",
          "amarket": true
        },
        {
          "name": "良信股份",
          "code": "002706",
          "percent": 0.92,
          "current_price": 29.79,
          "change_percentage": -2.77,
          "xq_symbol": "SZ002706",
          "xq_url": "https://xueqiu.com/S/SZ002706",
          "amarket": true
        },
        {
          "name": "桐昆股份",
          "code": "601233",
          "percent": 0.9,
          "current_price": 20.13,
          "change_percentage": -2.23,
          "xq_symbol": "SH601233",
          "xq_url": "https://xueqiu.com/S/SH601233",
          "amarket": true
        },
        {
          "name": "中材科技",
          "code": "002080",
          "percent": 0.9,
          "current_price": 24.75,
          "change_percentage": 2.36,
          "xq_symbol": "SZ002080",
          "xq_url": "https://xueqiu.com/S/SZ002080",
          "amarket": true
        }
      ],
      "bond_list": [
        {
          "name": "万孚转债",
          "code": "123064",
          "percent": 0.03,
          "xq_symbol": "123064",
          "xq_url": "https://xueqiu.com/S/123064",
          "amarket": false
        },
        {
          "name": "隆20转债",
          "code": "113038",
          "percent": 0.02,
          "xq_symbol": "113038",
          "xq_url": "https://xueqiu.com/S/113038",
          "amarket": false
        },
        {
          "name": "东缆转债",
          "code": "113603",
          "percent": 0.01,
          "xq_symbol": "113603",
          "xq_url": "https://xueqiu.com/S/113603",
          "amarket": false
        }
      ]
    },
    "fund_rates": {
      "fd_code": "001050",
      "subscribe_rate": "0",
      "declare_rate": "1.50",
      "withdraw_rate": "1.500",
      "discount": "0.1",
      "subscribe_discount": "0.1",
      "declare_discount": "0.1",
      "declare_rate_table": [
        {
          "name": "买入金额<100万",
          "value": "1.50"
        },
        {
          "name": "100万≤买入金额<200万",
          "value": "1.00"
        },
        {
          "name": "200万≤买入金额<500万",
          "value": "0.30"
        },
        {
          "name": "500万≤买入金额",
          "value": "1000.00"
        }
      ],
      "withdraw_rate_table": [
        {
          "name": "0天<持有期限<7天",
          "value": "1.500"
        },
        {
          "name": "7天≤持有期限<30天",
          "value": "0.750"
        },
        {
          "name": "30天≤持有期限<90天",
          "value": "0.500"
        },
        {
          "name": "3月≤持有期限<6月",
          "value": "0.500"
        },
        {
          "name": "6月≤持有期限",
          "value": "0.000"
        }
      ],
      "other_rate_table": [
        {
          "name": "基金托管费",
          "value": "0.25"
        },
        {
          "name": "基金管理费",
          "value": "1.50"
        }
      ]
    },
    "manager_list": [
      {
        "name": "吴振翔",
        "resume": "    吴振翔先生,国籍:中国,1977年出生,中国科学技术大学管理学博士,中国科学院数学与系统科学院应用数学专业博士后,14年证券从业经验。曾任长盛基金管理有限公司金融工程研究员、上投摩根基金管理有限公司产品开发高级经理。2008年3月加入汇添富基金管理股份有限公司,历任产品开发高级经理、数量投资高级分析师、基金经理助理,现任指数与量化投资部副总监。2010年2月5日至今任汇添富上证综合指数基金的基金经理,2011年9月16日至2013年11月7日任汇添富深证300ETF基金的基金经理,2011年9月28日至2013年11月7日任汇添富深证300ETF基金联接基金的基金经理,2013年8月23日至2015年11月2日任中证主要消费ETF基金、中证医药卫生ETF基金、中证能源ETF基金、中证金融地产ETF基金的基金经理,2013年11月6日至今任汇添富沪深300安中指数基金的基金经理,2015年2月16日至今任汇添富成长多因子股票基金的基金经理,2015年3月24日至今任汇添富主要消费ETF联接基金的基金经理,2016年1月21日至今任汇添富中证精准医指数基金的基金经理,2016年7月28日至今任中证上海国企ETF的基金经理,2016年12月22日至今任汇添富中证互联网医疗指数(LOF)的基金经理,2017年8月10日至今任汇添富中证500指数(LOF)的基金经理,2018年3月23日至今任添富价值多因子股票的基金经理,2019年7月26日至今任添富中证长三角ETF的基金经理,2019年9月24日至今任汇添富中证长三角ETF联接的基金经理,2019年11月6日任添富中证国企一带一路ETF的基金经理,2020年3月5日任添富中证国企一带一路ETF联接基金的基金经理。",
        "college": "中国科学院",
        "work_year": "15",
        "achievement_list": [
          {
            "fund_code": "010556",
            "fundsname": "汇添富沪深300指数增强C",
            "post_date": "2020-11-03",
            "cp_rate": 8.5219
          },
          {
            "fund_code": "005530",
            "fundsname": "汇添富沪深300指数增强A",
            "post_date": "2020-11-03",
            "cp_rate": 9.6009
          },
          {
            "fund_code": "008908",
            "fundsname": "添富中证国企一带一路ETF联接C",
            "post_date": "2020-03-05",
            "cp_rate": 26.28
          },
          {
            "fund_code": "008907",
            "fundsname": "添富中证国企一带一路ETF联接A",
            "post_date": "2020-03-05",
            "cp_rate": 26.6
          },
          {
            "fund_code": "515990",
            "fundsname": "添富中证国企一带一路ETF",
            "post_date": "2019-11-06",
            "cp_rate": 17.67
          },
          {
            "fund_code": "007839",
            "fundsname": "汇添富中证长三角ETF联接A",
            "post_date": "2019-09-24",
            "cp_rate": 28.57
          },
          {
            "fund_code": "007840",
            "fundsname": "汇添富中证长三角ETF联接C",
            "post_date": "2019-09-24",
            "cp_rate": 28.08
          },
          {
            "fund_code": "512650",
            "fundsname": "添富中证长三角ETF",
            "post_date": "2019-07-26",
            "cp_rate": 31.9447
          },
          {
            "fund_code": "005530",
            "fundsname": "汇添富价值多因子量化策略股票",
            "post_date": "2018-03-23",
            "resi_date": "2020-11-02",
            "cp_rate": 57.54
          },
          {
            "fund_code": "501037",
            "fundsname": "汇添富中证500指数(LOF)C",
            "post_date": "2017-08-10",
            "cp_rate": 8.4
          },
          {
            "fund_code": "501036",
            "fundsname": "汇添富中证500指数(LOF)A",
            "post_date": "2017-08-10",
            "cp_rate": 9.21
          },
          {
            "fund_code": "501008",
            "fundsname": "汇添富中证互联网医疗指数(LOF)C",
            "post_date": "2016-12-22",
            "cp_rate": 16.97
          },
          {
            "fund_code": "501007",
            "fundsname": "汇添富中证互联网医疗指数(LOF)A",
            "post_date": "2016-12-22",
            "cp_rate": 18.31
          },
          {
            "fund_code": "510810",
            "fundsname": "中证上海国企ETF",
            "post_date": "2016-07-28",
            "cp_rate": -4.9021
          },
          {
            "fund_code": "501006",
            "fundsname": "汇添富中证精准医指数C(LOF)",
            "post_date": "2016-01-21",
            "cp_rate": 71.38
          },
          {
            "fund_code": "501005",
            "fundsname": "汇添富中证精准医指数A(LOF)",
            "post_date": "2016-01-21",
            "cp_rate": 74.5104
          },
          {
            "fund_code": "000248",
            "fundsname": "汇添富中证主要消费ETF联接",
            "post_date": "2015-03-24",
            "cp_rate": 240.5057
          },
          {
            "fund_code": "001050",
            "fundsname": "汇添富成长多因子量化策略股票",
            "post_date": "2015-02-16",
            "cp_rate": 68.8
          },
          {
            "fund_code": "000368",
            "fundsname": "汇添富沪深300安中指数",
            "post_date": "2013-11-06",
            "cp_rate": 137.51
          },
          {
            "fund_code": "159931",
            "fundsname": "汇添富中证金融地产ETF",
            "post_date": "2013-08-23",
            "resi_date": "2015-11-02",
            "cp_rate": 44.2263
          },
          {
            "fund_code": "159930",
            "fundsname": "汇添富中证能源ETF",
            "post_date": "2013-08-23",
            "resi_date": "2015-11-02",
            "cp_rate": -10.0222
          },
          {
            "fund_code": "159928",
            "fundsname": "汇添富中证主要消费ETF",
            "post_date": "2013-08-23",
            "resi_date": "2015-11-02",
            "cp_rate": 34.451
          },
          {
            "fund_code": "159929",
            "fundsname": "汇添富中证医药卫生ETF",
            "post_date": "2013-08-23",
            "resi_date": "2015-11-02",
            "cp_rate": 47.2486
          },
          {
            "fund_code": "470068",
            "fundsname": "汇添富深证300ETF联接",
            "post_date": "2011-09-28",
            "resi_date": "2013-11-07",
            "cp_rate": -3.71
          },
          {
            "fund_code": "159912",
            "fundsname": "汇添富深证300ETF",
            "post_date": "2011-09-16",
            "resi_date": "2013-11-07",
            "cp_rate": -11.1722
          },
          {
            "fund_code": "470007",
            "fundsname": "汇添富上证综合指数",
            "post_date": "2010-02-05",
            "cp_rate": 53.9407
          }
        ]
      },
      {
        "name": "许一尊",
        "resume": "    许一尊先生,国籍:中国,上海财经大学经济学硕士,10年证券从业经验。2010年7月加入汇添富基金管理股份有限公司,现任指数与量化投资部高级分析师。2015年11月24日至今任汇添富成长多因子量化策略股票基金的基金经理,2018年3月23日至今任添富价值多因子股票基金的基金经理。",
        "college": "上海财经大学",
        "achievement_list": [
          {
            "fund_code": "005530",
            "fundsname": "汇添富沪深300指数增强A",
            "post_date": "2020-11-03",
            "cp_rate": 9.6009
          },
          {
            "fund_code": "010556",
            "fundsname": "汇添富沪深300指数增强C",
            "post_date": "2020-11-03",
            "cp_rate": 8.5219
          },
          {
            "fund_code": "005530",
            "fundsname": "汇添富价值多因子量化策略股票",
            "post_date": "2018-03-23",
            "resi_date": "2020-11-02",
            "cp_rate": 57.54
          },
          {
            "fund_code": "001050",
            "fundsname": "汇添富成长多因子量化策略股票",
            "post_date": "2015-11-24",
            "cp_rate": 45.2668
          }
        ]
      }
    ],
    "fund_date_conf": {
      "fd_code": "001050",
      "buy_confirm_date": 1,
      "buy_query_date": 1,
      "sale_confirm_date": 1,
      "sale_query_date": 2,
      "all_buy_days": 2,
      "all_sale_days": 3
    }
  },
  "result_code": 0
}