{
  "data": {
    "fund_company": "    上投摩根基金管理有限公司成立于2004年5月,总部位于上海,注册资本2.5亿元人民币。其中上海国际信托出资占比51%,摩根大通旗下摩根资产管理出资占比49%。集摩根资产管理150年享誉全球的专业资产管理经验,汇上海国际信托扎根本土的悠久品牌信誉,上投摩根传承中外股东精粹,致力于设立和管理证券投资基金,为不同类型的投资者提供多元化、国际领先的资产管理服务,成为值得信赖的长期合作伙伴。",
    "fund_position": {
      "stock_percent": 85.33,
      "bond_percent": 0.21,
      "cash_percent": 14.4,
      "other_percent": 0.06,
      "asset_tot": 758306835.24,
      "asset_val": 751844273.93,
      "source_mark": "第三季度报",
      "source": "4",
      "enddate": "2020-09-30",
      "stock_list": [
        {
          "name": "立讯精密",
          "code": "002475",
          "percent": 6.89,
          "current_price": 52.55,
          "change_percentage": -0.42,
          "xq_symbol": "SZ002475",
          "xq_url": "https://xueqiu.com/S/SZ002475",
          "amarket": true
        },
        {
          "name": "中国中免",
          "code": "601888",
          "percent": 6.57,
          "current_price": 208.03,
          "change_percentage": 0.13,
          "xq_symbol": "SH601888",
          "xq_url": "https://xueqiu.com/S/SH601888",
          "amarket": true
        },
        {
          "name": "隆基股份",
          "code": "601012",
          "percent": 5.77,
          "current_price": 72.54,
          "change_percentage": 1.14,
          "xq_symbol": "SH601012",
          "xq_url": "https://xueqiu.com/S/SH601012",
          "amarket": true
        },
        {
          "name": "歌尔股份",
          "code": "002241",
          "percent": 4.86,
          "current_price": 37.16,
          "change_percentage": -2.24,
          "xq_symbol": "SZ002241",
          "xq_url": "https://xueqiu.com/S/SZ002241",
          "amarket": true
        },
        {
          "name": "五粮液",
          "code": "000858",
          "percent": 4.85,
          "current_price": 272,
          "change_percentage": 0.65,
          "xq_symbol": "SZ000858",
          "xq_url": "https://xueqiu.com/S/SZ000858",
          "amarket": true
        },
        {
          "name": "拓普集团",
          "code": "601689",
          "percent": 3.95,
          "current_price": 38.54,
          "change_percentage": 3.66,
          "xq_symbol": "SH601689",
          "xq_url": "https://xueqiu.com/S/SH601689",
          "amarket": true
        },
        {
          "name": "浙江鼎力",
          "code": "603338",
          "percent": 3.83,
          "current_price": 103.96,
          "change_percentage": -2.04,
          "xq_symbol": "SH603338",
          "xq_url": "https://xueqiu.com/S/SH603338",
          "amarket": true
        },
        {
          "name": "恒立液压",
          "code": "601100",
          "percent": 3.26,
          "current_price": 96.79,
          "change_percentage": -1.59,
          "xq_symbol": "SH601100",
          "xq_url": "https://xueqiu.com/S/SH601100",
          "amarket": true
        },
        {
          "name": "爱尔眼科",
          "code": "300015",
          "percent": 3.2,
          "current_price": 66.63,
          "change_percentage": -0.25,
          "xq_symbol": "SZ300015",
          "xq_url": "https://xueqiu.com/S/SZ300015",
          "amarket": true
        },
        {
          "name": "凯莱英",
          "code": "002821",
          "percent": 3.13,
          "current_price": 274,
          "change_percentage": 1.64,
          "xq_symbol": "SZ002821",
          "xq_url": "https://xueqiu.com/S/SZ002821",
          "amarket": true
        }
      ],
      "bond_list": [
        {
          "name": "隆20转债",
          "code": "113038",
          "percent": 0.21,
          "xq_symbol": "113038",
          "xq_url": "https://xueqiu.com/S/113038",
          "amarket": false
        }
      ]
    },
    "fund_rates": {
      "fd_code": "001009",
      "subscribe_rate": "0",
      "declare_rate": "1.50",
      "withdraw_rate": "1.500",
      "discount": "0.1",
      "subscribe_discount": "0.1",
      "declare_discount": "0.1",
      "declare_rate_table": [
        {
          "name": "买入金额<100万",
          "value": "1.50"
        },
        {
          "name": "100万≤买入金额<500万",
          "value": "1.00"
        },
        {
          "name": "500万≤买入金额",
          "value": "1000.00"
        }
      ],
      "withdraw_rate_table": [
        {
          "name": "0天<持有期限<7天",
          "value": "1.500"
        },
        {
          "name": "7天≤持有期限<30天",
          "value": "0.750"
        },
        {
          "name": "30天≤持有期限<365天",
          "value": "0.500"
        },
        {
          "name": "1年≤持有期限<2年",
          "value": "0.350"
        },
        {
          "name": "2年≤持有期限<3年",
          "value": "0.200"
        },
        {
          "name": "3年≤持有期限",
          "value": "0.000"
        }
      ],
      "other_rate_table": [
        {
          "name": "基金托管费",
          "value": "0.25"
        },
        {
          "name": "基金管理费",
          "value": "1.50"
        }
      ]
    },
    "manager_list": [
      {
        "name": "陈思郁",
        "resume": "    陈思郁女士自2008年5月至2009年8月在国泰君安研究所担任研究员,自2009年9月起加入上投摩根基金管理有限公司,历任行业专家、基金经理助理,现任国内权益投资一部基金经理,自2015年8月起担任上投摩根双核平衡混合型证券投资基金基金经理,自2016年10月起同时担任上投摩根安全战略股票型证券投资基金基金经理。",
        "work_year": "12",
        "achievement_list": [
          {
            "fund_code": "001009",
            "fundsname": "上投摩根安全战略股票",
            "post_date": "2016-10-21",
            "cp_rate": 110.1965
          },
          {
            "fund_code": "373020",
            "fundsname": "上投摩根双核平衡混合",
            "post_date": "2015-08-04",
            "cp_rate": 106.0352
          }
        ]
      }
    ],
    "fund_date_conf": {
      "fd_code": "001009",
      "buy_confirm_date": 1,
      "buy_query_date": 1,
      "sale_confirm_date": 1,
      "sale_query_date": 3,
      "all_buy_days": 2,
      "all_sale_days": 4
    }
  },
  "result_code": 0
}